{"all":[{"id":281,"url":"https://leetcode.com/problems/zigzag-iterator","title":"Zigzag Iterator","difficulty":"Medium","acceptance":"66.5","frequency":"87.5"},{"id":68,"url":"https://leetcode.com/problems/text-justification","title":"Text Justification","difficulty":"Hard","acceptance":"50.4","frequency":"50.0"},{"id":588,"url":"https://leetcode.com/problems/design-in-memory-file-system","title":"Design In-Memory File System","difficulty":"Hard","acceptance":"48.4","frequency":"87.5"},{"id":1166,"url":"https://leetcode.com/problems/design-file-system","title":"Design File System","difficulty":"Medium","acceptance":"65.1","frequency":"62.5"},{"id":2325,"url":"https://leetcode.com/problems/decode-the-message","title":"Decode the Message","difficulty":"Easy","acceptance":"85.8","frequency":"75.0"},{"id":2043,"url":"https://leetcode.com/problems/simple-bank-system","title":"Simple Bank System","difficulty":"Medium","acceptance":"69.8","frequency":"100.0"},{"id":981,"url":"https://leetcode.com/problems/time-based-key-value-store","title":"Time Based Key-Value Store","difficulty":"Medium","acceptance":"49.7","frequency":"87.5"},{"id":3043,"url":"https://leetcode.com/problems/find-the-length-of-the-longest-common-prefix","title":"Find the Length of the Longest Common Prefix","difficulty":"Medium","acceptance":"57.0","frequency":"50.0"},{"id":528,"url":"https://leetcode.com/problems/random-pick-with-weight","title":"Random Pick with Weight","difficulty":"Medium","acceptance":"48.9","frequency":"75.0"},{"id":121,"url":"https://leetcode.com/problems/best-time-to-buy-and-sell-stock","title":"Best Time to Buy and Sell Stock","difficulty":"Easy","acceptance":"56.4","frequency":"50.0"},{"id":622,"url":"https://leetcode.com/problems/design-circular-queue","title":"Design Circular Queue","difficulty":"Medium","acceptance":"54.0","frequency":"50.0"}],"thirtyDays":[],"threeMonths":[{"id":528,"url":"https://leetcode.com/problems/random-pick-with-weight","title":"Random Pick with Weight","difficulty":"Medium","acceptance":"48.9","frequency":"100.0"}],"sixMonths":[{"id":2043,"url":"https://leetcode.com/problems/simple-bank-system","title":"Simple Bank System","difficulty":"Medium","acceptance":"69.8","frequency":"100.0"},{"id":588,"url":"https://leetcode.com/problems/design-in-memory-file-system","title":"Design In-Memory File System","difficulty":"Hard","acceptance":"48.4","frequency":"75.0"},{"id":528,"url":"https://leetcode.com/problems/random-pick-with-weight","title":"Random Pick with Weight","difficulty":"Medium","acceptance":"48.9","frequency":"100.0"}],"moreThanSixMonths":[{"id":281,"url":"https://leetcode.com/problems/zigzag-iterator","title":"Zigzag Iterator","difficulty":"Medium","acceptance":"66.5","frequency":"100.0"},{"id":588,"url":"https://leetcode.com/problems/design-in-memory-file-system","title":"Design In-Memory File System","difficulty":"Hard","acceptance":"48.4","frequency":"87.5"},{"id":1166,"url":"https://leetcode.com/problems/design-file-system","title":"Design File System","difficulty":"Medium","acceptance":"65.1","frequency":"62.5"},{"id":68,"url":"https://leetcode.com/problems/text-justification","title":"Text Justification","difficulty":"Hard","acceptance":"50.4","frequency":"62.5"},{"id":2043,"url":"https://leetcode.com/problems/simple-bank-system","title":"Simple Bank System","difficulty":"Medium","acceptance":"69.8","frequency":"100.0"},{"id":2325,"url":"https://leetcode.com/problems/decode-the-message","title":"Decode the Message","difficulty":"Easy","acceptance":"85.8","frequency":"62.5"},{"id":981,"url":"https://leetcode.com/problems/time-based-key-value-store","title":"Time Based Key-Value Store","difficulty":"Medium","acceptance":"49.7","frequency":"87.5"},{"id":3043,"url":"https://leetcode.com/problems/find-the-length-of-the-longest-common-prefix","title":"Find the Length of the Longest Common Prefix","difficulty":"Medium","acceptance":"57.0","frequency":"50.0"},{"id":528,"url":"https://leetcode.com/problems/random-pick-with-weight","title":"Random Pick with Weight","difficulty":"Medium","acceptance":"48.9","frequency":"50.0"},{"id":121,"url":"https://leetcode.com/problems/best-time-to-buy-and-sell-stock","title":"Best Time to Buy and Sell Stock","difficulty":"Easy","acceptance":"56.4","frequency":"50.0"}]}